desklank/__init__.py
desklank/__main__.py
desklank/__version__.py
desklank/config.py
desklank/node.py
desklank/peer.py
desklank/systray.py
desklank/page/__init__.py
desklank/page/connect.py
desklank/page/connection.py
desklank/page/labels.py
desklank/page/peer.py
desklank/page/peers.py
desklank-0.1.2.dist-info/LICENSE
desklank-0.1.2.dist-info/METADATA
desklank-0.1.2.dist-info/WHEEL
desklank-0.1.2.dist-info/entry_points.txt
desklank-0.1.2.dist-info/top_level.txt
desklank-0.1.2.dist-info/RECORD
