Metadata-Version: 2.1
Name: desklank
Version: 0.1.2
Summary: Text-mode peer-to-peer encrypted communication utilizing LANK protocol and DeskApp framework
Home-page: https://github.com/lannocc/desklank
Author: LANNOCC (Shawn A. Wilson)
Author-email: lannocc@yahoo.com
Classifier: Programming Language :: Python :: 3
Classifier: License :: OSI Approved :: MIT License
Classifier: Operating System :: OS Independent
License-File: LICENSE
Requires-Dist: appdirs
Requires-Dist: deskapp (>=0.0.4)
Requires-Dist: lank (>=0.4.7)
Requires-Dist: pillow
Requires-Dist: pystray
Requires-Dist: requests
